odoo/addons/product_uom_extra_data/README.rst
odoo/addons/product_uom_extra_data/__init__.py
odoo/addons/product_uom_extra_data/__manifest__.py
odoo/addons/product_uom_extra_data/data/product_uom.xml
odoo/addons/product_uom_extra_data/data/product_uom_categ.xml
odoo/addons/product_uom_extra_data/i18n/es.po
odoo/addons/product_uom_extra_data/i18n/fr.po
odoo/addons/product_uom_extra_data/i18n/hr.po
odoo/addons/product_uom_extra_data/i18n/it.po
odoo/addons/product_uom_extra_data/i18n/product_uom.pot
odoo/addons/product_uom_extra_data/static/description/icon.png
odoo11_addon_product_uom_extra_data-11.0.1.0.0.dist-info/METADATA
odoo11_addon_product_uom_extra_data-11.0.1.0.0.dist-info/RECORD
odoo11_addon_product_uom_extra_data-11.0.1.0.0.dist-info/WHEEL
odoo11_addon_product_uom_extra_data-11.0.1.0.0.dist-info/top_level.txt
